nonebot_plugin_ai_turtle_soup/__init__.py
nonebot_plugin_ai_turtle_soup/config.py
nonebot_plugin_ai_turtle_soup/game_manager.py
nonebot_plugin_ai_turtle_soup/prompts/gaming.md
nonebot_plugin_ai_turtle_soup/prompts/generate.md
nonebot_plugin_ai_turtle_soup/prompts/progress.md
nonebot_plugin_ai_turtle_soup/prompts/rate.md
nonebot_plugin_ai_turtle_soup-1.0.6.dist-info/licenses/LICENSE
nonebot_plugin_ai_turtle_soup-1.0.6.dist-info/METADATA
nonebot_plugin_ai_turtle_soup-1.0.6.dist-info/WHEEL
nonebot_plugin_ai_turtle_soup-1.0.6.dist-info/top_level.txt
nonebot_plugin_ai_turtle_soup-1.0.6.dist-info/RECORD
