Metadata-Version: 2.4
Name: nonebot-plugin-ai-turtle-soup
Version: 1.0.6
Summary: AI驱动的海龟汤(情境猜谜)游戏
Author-email: xxtg666 <xxtg666@gmail.com>
License: MIT
Requires-Python: >=3.9
License-File: LICENSE
Requires-Dist: nonebot2>=2.3.0
Requires-Dist: nonebot-plugin-alconna>=0.52.0
Requires-Dist: nonebot-plugin-uninfo>=0.9.0
Requires-Dist: openai>=2.3.0
Dynamic: license-file
